guiqwt/__init__.py
guiqwt/_cm.py
guiqwt/_scaler.cp310-win_amd64.pyd
guiqwt/annotations.py
guiqwt/baseplot.py
guiqwt/builder.py
guiqwt/colormap.py
guiqwt/config.py
guiqwt/cross_section.py
guiqwt/curve.py
guiqwt/debug.py
guiqwt/events.py
guiqwt/geometry.py
guiqwt/histogram.py
guiqwt/histogram2d.cp310-win_amd64.pyd
guiqwt/image.py
guiqwt/interfaces.py
guiqwt/io.py
guiqwt/label.py
guiqwt/mandelbrot.cp310-win_amd64.pyd
guiqwt/panels.py
guiqwt/plot.py
guiqwt/pyplot.py
guiqwt/qtdesigner.py
guiqwt/qthelpers.py
guiqwt/scaler.py
guiqwt/shapes.py
guiqwt/signals.py
guiqwt/styles.py
guiqwt/tools.py
guiqwt/transitional.py
guiqwt/images/arrow_down.png
guiqwt/images/arrow_up.png
guiqwt/images/autorefresh.png
guiqwt/images/axes.png
guiqwt/images/center.png
guiqwt/images/contrast.png
guiqwt/images/copytoclipboard.png
guiqwt/images/csapplylut.png
guiqwt/images/csautoscale.png
guiqwt/images/csection.png
guiqwt/images/csection_a.png
guiqwt/images/csection_oblique.png
guiqwt/images/csperimage.png
guiqwt/images/eliminate_outliers.png
guiqwt/images/eraser.png
guiqwt/images/export.png
guiqwt/images/font.png
guiqwt/images/full_range.png
guiqwt/images/funct.png
guiqwt/images/guiqwt.svg
guiqwt/images/hcursor.png
guiqwt/images/hflip.png
guiqwt/images/imagestats.png
guiqwt/images/item_list.png
guiqwt/images/magnifier.png
guiqwt/images/move.png
guiqwt/images/on_curve.png
guiqwt/images/point_selection.png
guiqwt/images/print.png
guiqwt/images/refresh.png
guiqwt/images/sift.svg
guiqwt/images/snapshot.png
guiqwt/images/trash.png
guiqwt/images/vcursor.png
guiqwt/images/vflip.png
guiqwt/images/xcursor.png
guiqwt/images/xrange.png
guiqwt/images/curvestyles/dots.png
guiqwt/images/curvestyles/lines.png
guiqwt/images/curvestyles/steps.png
guiqwt/images/curvestyles/sticks.png
guiqwt/images/curvetypes/xfy.png
guiqwt/images/curvetypes/yfx.png
guiqwt/images/items/annotation.png
guiqwt/images/items/curve.png
guiqwt/images/items/errorbar.png
guiqwt/images/items/grid.png
guiqwt/images/items/histogram.png
guiqwt-4.4.5.dist-info/Licence_CeCILL_V2-en.txt
guiqwt-4.4.5.dist-info/METADATA
guiqwt-4.4.5.dist-info/WHEEL
guiqwt-4.4.5.dist-info/entry_points.txt
guiqwt-4.4.5.dist-info/top_level.txt
guiqwt-4.4.5.dist-info/RECORD
