Metadata-Version: 2.1
Name: guiqwt
Version: 4.4.5
Summary: guiqwt is a set of tools for curve and image plotting (extension to PythonQwt)
Home-page: https://github.com/PlotPyStack/guiqwt
Author: Pierre Raybaut
Author-email: pierre.raybaut@gmail.com
License: CeCILL V2
Classifier: Topic :: Scientific/Engineering
Classifier: Operating System :: MacOS
Classifier: Operating System :: Microsoft :: Windows
Classifier: Operating System :: OS Independent
Classifier: Operating System :: POSIX
Classifier: Operating System :: Unix
Classifier: Programming Language :: Python :: 3
License-File: Licence_CeCILL_V2-en.txt
Requires-Dist: NumPy (>=1.3)
Requires-Dist: SciPy (>=0.7)
Requires-Dist: guidata (==3.1)
Requires-Dist: PythonQwt (>=0.10)
Requires-Dist: Pillow
Requires-Dist: QtPy (>=1.3)
Provides-Extra: dicom
Requires-Dist: pydicom (>=0.9.3) ; extra == 'dicom'
Provides-Extra: doc
Requires-Dist: Sphinx (>=1.1) ; extra == 'doc'
